CHANGES.md
MANIFEST.in
README.md
readme_pypi.rst
setup.cfg
setup.py
tabfix/__init__.py
tabfix/_version.py
tabfix/cmd_walker.py
tabfix/main.py
tabfix.egg-info/PKG-INFO
tabfix.egg-info/SOURCES.txt
tabfix.egg-info/dependency_links.txt
tabfix.egg-info/entry_points.txt
tabfix.egg-info/not-zip-safe
tabfix.egg-info/top_level.txt
tests/__init__.py
tests/test_all.py