Metadata-Version: 1.0
Name: tabfix
Version: 0.2.2
Summary: Cleanup whitespace in text files
Home-page: https://github.com/mar10/tabfix
Author: Martin Wendt
Author-email: tabfix@wwwendt.de
License: The MIT License
Keywords: python indentation development tab spaces tool
Platform: UNKNOWN
Classifier: Development Status :: 4 - Beta
Classifier: Environment :: Console
Classifier: Intended Audience :: Information Technology
Classifier: Intended Audience :: Developers
Classifier: License :: OSI Approved :: MIT License
Classifier: Operating System :: OS Independent
Classifier: Programming Language :: Python :: 2
Classifier: Programming Language :: Python :: 3
Classifier: Topic :: Software Development :: Libraries :: Python Modules
Classifier: Topic :: Utilities
